numthy.py
numthy-0.1.0.dist-info/licenses/LICENSE.md
numthy-0.1.0.dist-info/METADATA
numthy-0.1.0.dist-info/WHEEL
numthy-0.1.0.dist-info/top_level.txt
numthy-0.1.0.dist-info/RECORD
