Metadata-Version: 2.4
Name: numthy
Version: 0.1.0
Summary: Computational number theory. Pure Python. Zero dependencies. Unreasonably fast.
Author-email: Ini Oguntola <ioguntol@gmail.com>
License: MIT License
Project-URL: Homepage, https://github.com/ini/numthy
Project-URL: Documentation, https://github.com/ini/numthy/blob/main/API.md
Project-URL: Repository, https://github.com/ini/numthy
Keywords: number-theory,mathematics,primes,factorization,cryptography
Classifier: Development Status :: 4 - Beta
Classifier: Intended Audience :: Developers
Classifier: Intended Audience :: Science/Research
Classifier: License :: OSI Approved :: MIT License
Classifier: Operating System :: OS Independent
Classifier: Programming Language :: Python :: 3
Classifier: Programming Language :: Python :: 3.10
Classifier: Programming Language :: Python :: 3.11
Classifier: Programming Language :: Python :: 3.12
Classifier: Programming Language :: Python :: 3.13
Classifier: Programming Language :: Python :: 3.14
Classifier: Topic :: Scientific/Engineering :: Mathematics
Requires-Python: >=3.10
License-File: LICENSE.md
Dynamic: license-file
